lerax/__init__.py
lerax/utils.py
lerax/algorithm/__init__.py
lerax/algorithm/base_algorithm.py
lerax/algorithm/off_policy.py
lerax/algorithm/on_policy.py
lerax/algorithm/ppo.py
lerax/benchmark/__init__.py
lerax/buffer/__init__.py
lerax/buffer/base_buffer.py
lerax/buffer/replay.py
lerax/buffer/rollout.py
lerax/callback/__init__.py
lerax/callback/base_callback.py
lerax/callback/empty.py
lerax/callback/list.py
lerax/callback/progress_bar.py
lerax/callback/tensorboard.py
lerax/compatibility/__init__.py
lerax/compatibility/gym.py
lerax/compatibility/gymnax.py
lerax/distribution/__init__.py
lerax/distribution/base_distribution.py
lerax/distribution/bernoulli.py
lerax/distribution/categorical.py
lerax/distribution/multi_categorical.py
lerax/distribution/multivariate_normal.py
lerax/distribution/normal.py
lerax/distribution/squashed_multivariate_normal.py
lerax/distribution/squashed_normal.py
lerax/env/__init__.py
lerax/env/base_env.py
lerax/env/classic_control/__init__.py
lerax/env/classic_control/acrobot.py
lerax/env/classic_control/base_classic_control.py
lerax/env/classic_control/cartpole.py
lerax/env/classic_control/continuous_mountain_car.py
lerax/env/classic_control/mountain_car.py
lerax/env/classic_control/pendulum.py
lerax/env/mujoco/__init__.py
lerax/env/mujoco/base_mujoco.py
lerax/env/mujoco/humanoid.py
lerax/policy/__init__.py
lerax/policy/actor.py
lerax/policy/base_policy.py
lerax/policy/actor_critic/__init__.py
lerax/policy/actor_critic/base_actor_critic.py
lerax/policy/actor_critic/mlp.py
lerax/policy/q/__init__.py
lerax/policy/q/base_q.py
lerax/policy/q/mlp.py
lerax/render/__init__.py
lerax/render/base_renderer.py
lerax/render/mujoco_renderer.py
lerax/render/pygame_renderer.py
lerax/render/video.py
lerax/space/__init__.py
lerax/space/base_space.py
lerax/space/box.py
lerax/space/dict.py
lerax/space/discrete.py
lerax/space/multi_binary.py
lerax/space/multi_discrete.py
lerax/space/tuple.py
lerax/space/utils.py
lerax/wrapper/__init__.py
lerax-0.0.5.dist-info/licenses/LICENSE
lerax-0.0.5.dist-info/METADATA
lerax-0.0.5.dist-info/WHEEL
lerax-0.0.5.dist-info/top_level.txt
lerax-0.0.5.dist-info/RECORD
