Metadata-Version: 2.4
Name: lerax
Version: 0.0.5
Summary: Deep Reinforcement Learning with JAX and Equinox.
Author-email: Theodore Pinkerton <ted@tedpinkerton.ca>
License-Expression: GPL-3.0-or-later
Project-URL: documentation, https://lerax.tedpinkerton.ca/
Project-URL: homepage, https://lerax.tedpinkerton.ca/
Project-URL: issues, https://github.com/RunnersNum40/lerax/issues
Project-URL: source, https://github.com/RunnersNum40/lerax.git
Requires-Python: >=3.13
License-File: LICENSE
Requires-Dist: diffrax
Requires-Dist: distreqx>=0.0.2
Requires-Dist: equinox
Requires-Dist: jax
Requires-Dist: jaxtyping
Requires-Dist: optax
Requires-Dist: rich
Requires-Dist: tensorboard
Requires-Dist: tensorboardX
Provides-Extra: compatibility
Requires-Dist: gymnasium; extra == "compatibility"
Requires-Dist: stable-baselines3; extra == "compatibility"
Requires-Dist: gymnax; extra == "compatibility"
Requires-Dist: flax; extra == "compatibility"
Provides-Extra: docs
Requires-Dist: zensical; extra == "docs"
Requires-Dist: mkdocstrings-python; extra == "docs"
Provides-Extra: mujoco
Requires-Dist: mujoco-mjx; extra == "mujoco"
Provides-Extra: render
Requires-Dist: pygame; extra == "render"
Requires-Dist: imageio; extra == "render"
Requires-Dist: imageio-ffmpeg; extra == "render"
Dynamic: license-file
